[
  {
    "uuid": "e168794d-2a52-3639-938f-43fcc62c6ea4",
    "name": "D4rkG",
    "level": 4,
    "bypassesPlayerLimit": false
  },
  {
    "uuid": "19671aba-715a-37b6-a1b6-ed952f2417ed",
    "name": "fakhinho",
    "level": 4,
    "bypassesPlayerLimit": false
  },
  {
    "uuid": "5296e45c-d886-344c-b5d8-7059dc7a7d51",
    "name": "desistokkk",
    "level": 4,
    "bypassesPlayerLimit": false
  },
  {
    "uuid": "6bc8a64d-a45a-3825-82f0-bc1261502aab",
    "name": "lincolncpp",
    "level": 4,
    "bypassesPlayerLimit": false
  },
  {
    "uuid": "4053a3c3-7644-3ac8-9953-e84661b90056",
    "name": "preiforthecha",
    "level": 4,
    "bypassesPlayerLimit": false
  },
  {
    "uuid": "2576b041-2329-4256-90ba-e4650989c489",
    "name": "all",
    "level": 4,
    "bypassesPlayerLimit": false
  },
  {
    "uuid": "41d5c862-17b7-3483-a2cc-3e1f5b7dddba",
    "name": "tourist",
    "level": 4,
    "bypassesPlayerLimit": false
  }
]